smaliemu/__init__.py
smaliemu/emulator.py
smaliemu/exception.py
smaliemu/object_mapping.py
smaliemu/opcodes.py
smaliemu/preprocessors.py
smaliemu/snippet.py
smaliemu/source.py
smaliemu/vm.py
smaliemu/objects/__init__.py
smaliemu/objects/string.py
smaliemu/objects/string_buffer.py
smaliemu/objects/string_builder.py
smaliemu-0.1.11.dist-info/METADATA
smaliemu-0.1.11.dist-info/RECORD
smaliemu-0.1.11.dist-info/WHEEL
smaliemu-0.1.11.dist-info/top_level.txt
