Metadata-Version: 2.1
Name: smaliemu
Version: 0.1.11
Summary: smaliemu
Home-page: https://github.com/mikusjelly/smaliemu
Author: mikusjelly
Author-email: mikusjelly@gmail.com
License: GPL V3
Platform: UNKNOWN
Classifier: Development Status :: 4 - Beta
Classifier: License :: OSI Approved :: Apache Software License
Classifier: Programming Language :: Python :: 3 :: Only
Classifier: Topic :: Utilities
